dnctree/__init__.py
dnctree/algtesting.py
dnctree/distances.py
dnctree/dnctree_k.py
dnctree/exceptions.py
dnctree/main.py
dnctree/msa.py
dnctree/pahmm_adaptor.py
dnctree/partialdistancematrix.py
dnctree/stupid_tree.py
dnctree/tree.py
dnctree/version.py
dnctree-1.0.1.dist-info/LICENSE
dnctree-1.0.1.dist-info/METADATA
dnctree-1.0.1.dist-info/WHEEL
dnctree-1.0.1.dist-info/entry_points.txt
dnctree-1.0.1.dist-info/top_level.txt
dnctree-1.0.1.dist-info/RECORD
