Metadata-Version: 2.1
Name: dnctree
Version: 1.0.1
Summary: Distance-based phylogeny inference using a randomised divide-and-conquer method
Author-email: Lars Arvestad <arve@math.su.se>, Amy Lee Jalenius <amy.jalsenius@gmail.com>
Maintainer-email: Lars Arvestad <arve@math.su.se>
License: GNU General Public License v3 (GPLv3)
Project-URL: homepage, https://github.com/arvestad/dnctree
Classifier: Programming Language :: Python :: 3
Classifier: License :: OSI Approved :: GNU General Public License v3 (GPLv3)
Classifier: Operating System :: OS Independent
Classifier: Topic :: Scientific/Engineering :: Bio-Informatics
License-File: LICENSE
Requires-Dist: alv >=1.5
Requires-Dist: modelmatcher >=1.1.3
Requires-Dist: biopython >=1.81
Requires-Dist: ete3 >=3.1.1
Requires-Dist: tree-matching-distance
